{
    "data": {
        "list": [
            {
                "id": 898, 
                "pid": 0, 
                "title": "5月当季推荐", 
                "subtitle": "伸手接住五月的阳光", 
                "content": "", 
                "mddid": 0, 
                "mddname": "", 
                "poi_id": 0, 
                "poi_name": "", 
                "url": "", 
                "icon": "", 
                "style": "mdd", 
                "sort": 102, 
                "flag": 0, 
                "ctime": "2015-04-24 15:38:11", 
                "utime": "2015-09-10 10:27:59", 
                "target_id": 0, 
                "items": [
                    {
                        "id": 902, 
                        "title": "南浔", 
                        "subtitle": "一幕雨帘独自清", 
                        "img": "http://file105.mafengwo.net/s8/M00/7D/96/wKgBpVU6BXaAb3FhAAP8xhMjsbw60.jpeg", 
                        "url": "http://m.mafengwo.cn/nb/public/sharejump.php?type=10&id=10089"
                    }, 
                    {
                        "id": 901, 
                        "title": "青海", 
                        "subtitle": "享骑行时光，览青海湖色", 
                        "img": "http://file107.mafengwo.net/s8/M00/7D/83/wKgBpVU6BWKAIsZXAAHqMvzIw6s35.jpeg", 
                        "url": "http://m.mafengwo.cn/nb/public/sharejump.php?type=10&id=12788"
                    }, 
                    {
                        "id": 906, 
                        "title": "泸沽湖", 
                        "subtitle": "东方女儿国", 
                        "img": "http://file101.mafengwo.net/s8/M00/7E/91/wKgBpVU6BnyAVSHcAAMEZaraeOA52.jpeg", 
                        "url": "http://m.mafengwo.cn/nb/public/sharejump.php?type=10&id=10121"
                    }, 
                    {
                        "id": 908, 
                        "title": "曼谷", 
                        "subtitle": "身体和心灵都在路上", 
                        "img": "http://file102.mafengwo.net/s8/M00/81/1A/wKgBpVU6CMOAXaXoAAF7-SrKTFI50.jpeg", 
                        "url": "http://m.mafengwo.cn/nb/public/sharejump.php?type=10&id=11045"
                    }, 
                    {
                        "id": 911, 
                        "title": "普吉岛", 
                        "subtitle": "停下来，趁阳光正好", 
                        "img": "http://file112.mafengwo.net/s8/M00/96/A0/wKgBpVU6G72AZp0yAANyRm1LPsM09.jpeg", 
                        "url": "http://m.mafengwo.cn/nb/public/sharejump.php?type=10&id=11047"
                    }, 
                    {
                        "id": 899, 
                        "title": "拉萨", 
                        "subtitle": "行走在云端", 
                        "img": "http://file108.mafengwo.net/s8/M00/7D/6C/wKgBpVU6BTeAHs3jAAb_gkIDETI15.jpeg", 
                        "url": "http://m.mafengwo.cn/nb/public/sharejump.php?type=10&id=10442"
                    }, 
                    {
                        "id": 905, 
                        "title": "菲律宾", 
                        "subtitle": "沙滩海岸，想入菲菲", 
                        "img": "http://file107.mafengwo.net/s8/M00/7D/E5/wKgBpVU6Bc6ARoMzAALK59IWXcA21.jpeg", 
                        "url": "http://m.mafengwo.cn/nb/public/sharejump.php?type=10&id=10067"
                    }, 
                    {
                        "id": 912, 
                        "title": "首尔", 
                        "subtitle": "go！购！够！", 
                        "img": "http://file102.mafengwo.net/s8/M00/98/F8/wKgBpVU6HjOARKLAAARiqGtQTBE95.jpeg", 
                        "url": "http://m.mafengwo.cn/nb/public/sharejump.php?type=10&id=10130"
                    }, 
                    {
                        "id": 909, 
                        "title": "土耳其", 
                        "subtitle": "日光倾城，土国童话", 
                        "img": "http://file112.mafengwo.net/s8/M00/8B/C0/wKgBpVU6EZKAN_vhAAF7PH3Jv6g90.jpeg", 
                        "url": "http://m.mafengwo.cn/nb/public/sharejump.php?type=10&id=10053"
                    }, 
                    {
                        "id": 904, 
                        "title": "香格里拉", 
                        "subtitle": "距天堂最近的地方", 
                        "img": "http://file106.mafengwo.net/s8/M00/7D/D5/wKgBpVU6BbiAK_XLAAOD5EOQmdU99.jpeg", 
                        "url": "http://m.mafengwo.cn/nb/public/sharejump.php?type=10&id=10482"
                    }, 
                    {
                        "id": 907, 
                        "title": "桂林", 
                        "subtitle": "浓墨重彩，景甲天下", 
                        "img": "http://file101.mafengwo.net/s8/M00/7E/E7/wKgBpVU6BuyAbFICAAKl-ssv6aE82.jpeg", 
                        "url": "http://m.mafengwo.cn/nb/public/sharejump.php?type=10&id=10095"
                    }, 
                    {
                        "id": 910, 
                        "title": "香港", 
                        "subtitle": "市井香港", 
                        "img": "http://file104.mafengwo.net/s8/M00/92/8B/wKgBpVU6F4-AINmeAAJEqkDPnEk42.jpeg", 
                        "url": "http://m.mafengwo.cn/nb/public/sharejump.php?type=10&id=10189"
                    }, 
                    {
                        "id": 914, 
                        "title": "青岛", 
                        "subtitle": "走不完的美", 
                        "img": "http://file110.mafengwo.net/s8/M00/7D/77/wKgBpVU6BU6AK0qhAANvE8Uh7JY86.jpeg", 
                        "url": "http://m.mafengwo.cn/nb/public/sharejump.php?type=10&id=10444"
                    }, 
                    {
                        "id": 913, 
                        "title": "平遥", 
                        "subtitle": "西去北往，一眼平遥", 
                        "img": "http://file105.mafengwo.net/s8/M00/7D/BE/wKgBpVU6BaCACKrQAAMAzJowxgA69.jpeg", 
                        "url": "http://m.mafengwo.cn/nb/public/sharejump.php?type=10&id=10547"
                    }
                ]
            }
        ], 
        "has_more": 0
    }, 
    "is_array": 1
}